__init__.py
example.py
items.py
main.py
template_python_test-0.0.0.dist-info/LICENSE
template_python_test-0.0.0.dist-info/METADATA
template_python_test-0.0.0.dist-info/WHEEL
template_python_test-0.0.0.dist-info/RECORD
