Metadata-Version: 2.1
Name: template-python-test
Version: 0.0.0
Summary: Web service template in Python for reuse.
Home-page: https://github.com/Shockedshodan/template-python-test
License: MIT
Author: HIRO-MicroDataCenters
Author-email: all-hiro@hiro-microdatacenters.nl
Requires-Python: >=3.10,<4.0
Classifier: License :: OSI Approved :: MIT License
Classifier: Programming Language :: Python :: 3
Classifier: Programming Language :: Python :: 3.10
Classifier: Programming Language :: Python :: 3.11
Classifier: Programming Language :: Python :: 3.12
Requires-Dist: classy-fastapi (>=0.6.1,<0.7.0)
Requires-Dist: fastapi (>=0.109,<0.110)
Requires-Dist: uvicorn (>=0.26,<0.27)
Project-URL: Repository, https://github.com/Shockedshodan/template-python-test
